euklid.cp312-win_amd64.pyd
euklid-stubs/__init__.pyi
euklid-stubs/mesh.pyi
euklid-stubs/plane.pyi
euklid-stubs/spline.pyi
euklid-stubs/vector.pyi
euklid-0.2.6.dist-info/LICENSE
euklid-0.2.6.dist-info/METADATA
euklid-0.2.6.dist-info/WHEEL
euklid-0.2.6.dist-info/top_level.txt
euklid-0.2.6.dist-info/RECORD
