Metadata-Version: 2.1
Name: euklid
Version: 0.2.6
Summary: common vector operations [2D/3D]
Home-page: http://github.com/airgproducts/euklid
Author: airgproducts
License: MIT
License-File: LICENSE
